rasterix/__init__.py
rasterix/_version.py
rasterix/odc_compat.py
rasterix/raster_index.py
rasterix/rioxarray_compat.py
rasterix/utils.py
rasterix/rasterize/__init__.py
rasterix/rasterize/exact.py
rasterix/rasterize/rasterio.py
rasterix/rasterize/utils.py
rasterix-0.1a4.dist-info/METADATA
rasterix-0.1a4.dist-info/WHEEL
rasterix-0.1a4.dist-info/licenses/LICENSE
rasterix-0.1a4.dist-info/RECORD
