Metadata-Version: 2.4
Name: rasterix
Version: 0.1a4
Summary: Raster extensions for Xarray
License-Expression: Apache-2.0
License-File: LICENSE
Keywords: xarray
Classifier: Development Status :: 4 - Beta
Classifier: Natural Language :: English
Classifier: Operating System :: OS Independent
Classifier: Programming Language :: Python
Classifier: Programming Language :: Python :: 3.11
Classifier: Programming Language :: Python :: 3.12
Classifier: Programming Language :: Python :: 3.13
Requires-Python: >=3.11
Requires-Dist: affine
Requires-Dist: numpy>=2
Requires-Dist: pandas>=2
Requires-Dist: xarray>=2025
Requires-Dist: xproj>=0.2.0
Provides-Extra: dask
Requires-Dist: dask-geopandas; extra == 'dask'
Provides-Extra: docs
Requires-Dist: dask-geopandas; extra == 'docs'
Requires-Dist: exactextract; extra == 'docs'
Requires-Dist: furo; extra == 'docs'
Requires-Dist: geodatasets; extra == 'docs'
Requires-Dist: myst-nb; extra == 'docs'
Requires-Dist: myst-parser; extra == 'docs'
Requires-Dist: netcdf4; extra == 'docs'
Requires-Dist: numpydoc; extra == 'docs'
Requires-Dist: pooch; extra == 'docs'
Requires-Dist: rasterio; extra == 'docs'
Requires-Dist: rioxarray; extra == 'docs'
Requires-Dist: sparse; extra == 'docs'
Requires-Dist: sphinx; extra == 'docs'
Requires-Dist: sphinx-autoapi; extra == 'docs'
Requires-Dist: sphinx-autobuild>=2021.3.14; extra == 'docs'
Requires-Dist: sphinx-codeautolink; extra == 'docs'
Requires-Dist: sphinx-copybutton; extra == 'docs'
Requires-Dist: sphinx-remove-toctrees; extra == 'docs'
Requires-Dist: sphinxext-opengraph[social-cards]; extra == 'docs'
Provides-Extra: exactextract
Requires-Dist: exactextract; extra == 'exactextract'
Requires-Dist: sparse; extra == 'exactextract'
Provides-Extra: rasterize
Requires-Dist: rasterio; extra == 'rasterize'
Provides-Extra: test
Requires-Dist: dask-geopandas; extra == 'test'
Requires-Dist: exactextract; extra == 'test'
Requires-Dist: geodatasets; extra == 'test'
Requires-Dist: hypothesis; extra == 'test'
Requires-Dist: netcdf4; extra == 'test'
Requires-Dist: pooch; extra == 'test'
Requires-Dist: rasterio; extra == 'test'
Requires-Dist: sparse; extra == 'test'
